[
  {
    "placeObjects": [
      {
        "depth": 2,
        "id": 2235
      }
    ],
    "removeObjects": [],
    "label": "Longsword"
  },
  {
    "placeObjects": [],
    "removeObjects": [
      {
        "depth": 2
      }
    ],
    "label": "none"
  },
  {
    "placeObjects": [
      {
        "depth": 4,
        "id": 2236
      }
    ],
    "removeObjects": [],
    "label": "Sun Sword"
  },
  {
    "placeObjects": [
      {
        "depth": 3,
        "id": 2237
      }
    ],
    "removeObjects": [
      {
        "depth": 4
      }
    ],
    "label": "M Blade"
  },
  {
    "placeObjects": [
      {
        "depth": 1,
        "id": 2238
      }
    ],
    "removeObjects": [
      {
        "depth": 3
      }
    ],
    "label": "Stick"
  },
  {
    "placeObjects": [
      {
        "depth": 2,
        "id": 2239
      }
    ],
    "removeObjects": [
      {
        "depth": 1
      }
    ],
    "label": "Bronze Sword"
  },
  {
    "placeObjects": [
      {
        "depth": 3,
        "id": 2240
      }
    ],
    "removeObjects": [
      {
        "depth": 2
      }
    ],
    "label": "Silver Sword"
  },
  {
    "placeObjects": [
      {
        "depth": 2,
        "id": 2241
      }
    ],
    "removeObjects": [
      {
        "depth": 3
      }
    ],
    "label": "Mace"
  },
  {
    "placeObjects": [
      {
        "depth": 1,
        "id": 2242
      }
    ],
    "removeObjects": [
      {
        "depth": 2
      }
    ],
    "label": "Keyblade"
  },
  {
    "placeObjects": [
      {
        "depth": 2,
        "id": 2243
      }
    ],
    "removeObjects": [
      {
        "depth": 1
      }
    ],
    "label": "Iron Sword"
  },
  {
    "placeObjects": [
      {
        "depth": 1,
        "id": 2244
      }
    ],
    "removeObjects": [
      {
        "depth": 2
      }
    ],
    "label": "Shadowblade"
  },
  {
    "placeObjects": [
      {
        "depth": 2,
        "id": 2245
      }
    ],
    "removeObjects": [
      {
        "depth": 1
      }
    ],
    "label": "Champion Sword"
  },
  {
    "placeObjects": [
      {
        "depth": 1,
        "id": 2246
      }
    ],
    "removeObjects": [
      {
        "depth": 2
      }
    ],
    "label": "Mythril Sword"
  },
  {
    "placeObjects": [
      {
        "depth": 1,
        "id": 2247
      }
    ],
    "removeObjects": [],
    "label": "xantusian scimitar"
  },
  {
    "placeObjects": [
      {
        "depth": 3,
        "id": 2248
      }
    ],
    "removeObjects": [
      {
        "depth": 1
      }
    ],
    "label": "Aeropolitan Scimitar"
  },
  {
    "placeObjects": [
      {
        "depth": 6,
        "id": 2249
      }
    ],
    "removeObjects": [
      {
        "depth": 3
      }
    ],
    "label": "Flametongue"
  },
  {
    "placeObjects": [
      {
        "depth": 3,
        "id": 2250
      }
    ],
    "removeObjects": [
      {
        "depth": 6
      }
    ],
    "label": "Fishslayer"
  },
  {
    "placeObjects": [
      {
        "depth": 4,
        "id": 2251
      }
    ],
    "removeObjects": [
      {
        "depth": 3
      }
    ],
    "label": "Blood Sword"
  },
  {
    "placeObjects": [
      {
        "depth": 1,
        "id": 2252
      },
      {
        "depth": 2,
        "id": 2254,
        "translateX": 0.1,
        "translateY": -19.7,
        "glowBlurXandY": 10.0,
        "glowStrengh": 1.0,
        "glowColorRGBA": [
          255,
          255,
          255,
          255
        ]
      },
      {
        "depth": 5,
        "id": 2255
      }
    ],
    "removeObjects": [
      {
        "depth": 4
      }
    ],
    "label": "Righteous Justice"
  },
  {
    "placeObjects": [
      {
        "depth": 3,
        "id": 2256
      }
    ],
    "removeObjects": [
      {
        "depth": 1
      },
      {
        "depth": 2
      },
      {
        "depth": 5
      }
    ],
    "label": "Clerical Mace"
  },
  {
    "placeObjects": [
      {
        "depth": 5,
        "id": 2257
      }
    ],
    "removeObjects": [
      {
        "depth": 3
      }
    ],
    "label": "Forest Edge"
  },
  {
    "placeObjects": [
      {
        "depth": 3,
        "id": 2258
      }
    ],
    "removeObjects": [
      {
        "depth": 5
      }
    ],
    "label": "sword of goznor"
  },
  {
    "placeObjects": [
      {
        "depth": 2,
        "id": 2259
      }
    ],
    "removeObjects": [
      {
        "depth": 3
      }
    ],
    "label": "Champion Sword II"
  },
  {
    "placeObjects": [
      {
        "depth": 2,
        "id": 2260
      }
    ],
    "removeObjects": [],
    "label": "Cursed Blade"
  },
  {
    "placeObjects": [],
    "removeObjects": []
  },
  {
    "placeObjects": [],
    "removeObjects": []
  },
  {
    "placeObjects": [],
    "removeObjects": []
  },
  {
    "placeObjects": [],
    "removeObjects": []
  },
  {
    "placeObjects": [],
    "removeObjects": []
  },
  {
    "placeObjects": [],
    "removeObjects": []
  },
  {
    "placeObjects": [],
    "removeObjects": []
  },
  {
    "placeObjects": [],
    "removeObjects": []
  },
  {
    "placeObjects": [],
    "removeObjects": []
  },
  {
    "placeObjects": [],
    "removeObjects": []
  },
  {
    "placeObjects": [],
    "removeObjects": []
  },
  {
    "placeObjects": [],
    "removeObjects": []
  }
]