[
  {
    "placeObjects": [
      {
        "depth": 2,
        "id": 2513
      }
    ],
    "removeObjects": [],
    "label": "guardian"
  },
  {
    "placeObjects": [
      {
        "depth": 1,
        "id": 2514
      }
    ],
    "removeObjects": [
      {
        "depth": 2
      }
    ],
    "label": "soldier"
  },
  {
    "placeObjects": [],
    "removeObjects": []
  },
  {
    "placeObjects": [],
    "removeObjects": []
  },
  {
    "placeObjects": [],
    "removeObjects": []
  },
  {
    "placeObjects": [],
    "removeObjects": []
  },
  {
    "placeObjects": [],
    "removeObjects": []
  },
  {
    "placeObjects": [],
    "removeObjects": []
  },
  {
    "placeObjects": [],
    "removeObjects": []
  },
  {
    "placeObjects": [
      {
        "depth": 1,
        "id": 2388
      }
    ],
    "removeObjects": [],
    "label": "hero_LL"
  }
]