[
  {
    "placeObjects": [
      {
        "depth": 1,
        "id": 3223
      }
    ],
    "removeObjects": [],
    "label": "D"
  },
  {
    "placeObjects": [
      {
        "depth": 1,
        "id": 3224
      }
    ],
    "removeObjects": [],
    "label": "posh"
  },
  {
    "placeObjects": [
      {
        "depth": 1,
        "id": 3225
      }
    ],
    "removeObjects": [],
    "label": "hob"
  },
  {
    "placeObjects": [
      {
        "depth": 1,
        "id": 3226
      }
    ],
    "removeObjects": [],
    "label": "poor"
  },
  {
    "placeObjects": [
      {
        "depth": 1,
        "id": 3227
      }
    ],
    "removeObjects": [],
    "label": "elf"
  },
  {
    "placeObjects": [],
    "removeObjects": []
  },
  {
    "placeObjects": [],
    "removeObjects": []
  },
  {
    "placeObjects": [],
    "removeObjects": []
  },
  {
    "placeObjects": [],
    "removeObjects": []
  },
  {
    "placeObjects": [
      {
        "depth": 1,
        "id": 3228
      }
    ],
    "removeObjects": [],
    "label": "D_LL"
  },
  {
    "placeObjects": [
      {
        "depth": 1,
        "id": 3229
      }
    ],
    "removeObjects": [],
    "label": "posh_LL"
  }
]