[
  {
    "placeObjects": [
      {
        "depth": 1,
        "id": 3586
      }
    ],
    "removeObjects": [],
    "label": "d"
  },
  {
    "placeObjects": [
      {
        "depth": 1,
        "id": 3587
      }
    ],
    "removeObjects": [],
    "label": "gem"
  },
  {
    "placeObjects": [
      {
        "depth": 1,
        "id": 3588
      }
    ],
    "removeObjects": [],
    "label": "amber"
  },
  {
    "placeObjects": [
      {
        "depth": 1,
        "id": 3589
      }
    ],
    "removeObjects": [],
    "label": "dark"
  }
]