[
  {
    "placeObjects": [
      {
        "depth": 3,
        "id": 4054
      }
    ],
    "removeObjects": [],
    "label": "c"
  },
  {
    "placeObjects": [
      {
        "depth": 2,
        "id": 4055
      }
    ],
    "removeObjects": [
      {
        "depth": 3
      }
    ],
    "label": "m"
  },
  {
    "placeObjects": [
      {
        "depth": 3,
        "id": 4056
      }
    ],
    "removeObjects": [
      {
        "depth": 2
      }
    ],
    "label": "p"
  },
  {
    "placeObjects": [
      {
        "depth": 3,
        "id": 4057
      }
    ],
    "removeObjects": [],
    "label": "s"
  },
  {
    "placeObjects": [],
    "removeObjects": []
  },
  {
    "placeObjects": [],
    "removeObjects": []
  },
  {
    "placeObjects": [],
    "removeObjects": []
  },
  {
    "placeObjects": [
      {
        "depth": 3,
        "id": 4058
      }
    ],
    "removeObjects": []
  },
  {
    "placeObjects": [],
    "removeObjects": []
  },
  {
    "placeObjects": [],
    "removeObjects": []
  },
  {
    "placeObjects": [],
    "removeObjects": []
  },
  {
    "placeObjects": [],
    "removeObjects": []
  },
  {
    "placeObjects": [],
    "removeObjects": []
  },
  {
    "placeObjects": [],
    "removeObjects": []
  },
  {
    "placeObjects": [],
    "removeObjects": []
  },
  {
    "placeObjects": [],
    "removeObjects": []
  },
  {
    "placeObjects": [],
    "removeObjects": []
  },
  {
    "placeObjects": [],
    "removeObjects": []
  },
  {
    "placeObjects": [],
    "removeObjects": []
  },
  {
    "placeObjects": [],
    "removeObjects": []
  },
  {
    "placeObjects": [],
    "removeObjects": []
  },
  {
    "placeObjects": [],
    "removeObjects": []
  },
  {
    "placeObjects": [],
    "removeObjects": []
  },
  {
    "placeObjects": [],
    "removeObjects": []
  },
  {
    "placeObjects": [
      {
        "depth": 3,
        "id": 4059
      }
    ],
    "removeObjects": []
  },
  {
    "placeObjects": [],
    "removeObjects": []
  },
  {
    "placeObjects": [],
    "removeObjects": []
  },
  {
    "placeObjects": [],
    "removeObjects": []
  },
  {
    "placeObjects": [],
    "removeObjects": []
  },
  {
    "placeObjects": [],
    "removeObjects": []
  },
  {
    "placeObjects": [
      {
        "depth": 3,
        "id": 4060
      }
    ],
    "removeObjects": []
  },
  {
    "placeObjects": [
      {
        "depth": 3,
        "id": 4061
      }
    ],
    "removeObjects": []
  }
]