[
  {
    "placeObjects": [
      {
        "depth": 1,
        "id": 4133
      }
    ],
    "removeObjects": [],
    "label": "earth"
  },
  {
    "placeObjects": [
      {
        "depth": 1,
        "id": 4134
      }
    ],
    "removeObjects": [],
    "label": "water"
  },
  {
    "placeObjects": [
      {
        "depth": 1,
        "id": 4135
      }
    ],
    "removeObjects": [],
    "label": "fire"
  },
  {
    "placeObjects": [
      {
        "depth": 1,
        "id": 4136
      }
    ],
    "removeObjects": [],
    "label": "dark"
  }
]